README.rst
setup.py
python_zenity.egg-info/PKG-INFO
python_zenity.egg-info/SOURCES.txt
python_zenity.egg-info/dependency_links.txt
python_zenity.egg-info/not-zip-safe
python_zenity.egg-info/top_level.txt
pythonzenity/__init__.py
pythonzenity/python_zenity.py