Metadata-Version: 1.0
Name: python-zenity
Version: 0.1.2
Summary: Simple dialog with Python and Gtk
Home-page: http://github.com/poulp/python-zenity
Author: poulp
Author-email: mathieu.nerv@gmail.com
License: MIT
Platform: UNKNOWN
